<annotation>
	<folder>training data</folder>
	<filename>IMG_20210415_124602.jpg</filename>
	<path>D:\Document\UTB notes\Cipta 2021\training data\IMG_20210415_124602.jpg</path>
	<source>
		<database>Unknown</database>
	</source>
	<size>
		<width>2736</width>
		<height>3648</height>
		<depth>3</depth>
	</size>
	<segmented>0</segmented>
	<object>
		<name>Side Junction on the left 300m Ahead</name>
		<pose>Unspecified</pose>
		<truncated>0</truncated>
		<difficult>0</difficult>
		<bndbox>
			<xmin>2094</xmin>
			<ymin>996</ymin>
			<xmax>2270</xmax>
			<ymax>1288</ymax>
		</bndbox>
	</object>
</annotation>
